entari_plugin_hyw/__init__.py
entari_plugin_hyw/assets/package-lock.json
entari_plugin_hyw/assets/package.json
entari_plugin_hyw/assets/tailwind.config.js
entari_plugin_hyw/assets/tailwind.input.css
entari_plugin_hyw/assets/template.html
entari_plugin_hyw/assets/template.html.bak
entari_plugin_hyw/assets/template.j2
entari_plugin_hyw/assets/icon/anthropic.svg
entari_plugin_hyw/assets/icon/cerebras.svg
entari_plugin_hyw/assets/icon/deepseek.png
entari_plugin_hyw/assets/icon/gemini.svg
entari_plugin_hyw/assets/icon/google.svg
entari_plugin_hyw/assets/icon/grok.png
entari_plugin_hyw/assets/icon/huggingface.png
entari_plugin_hyw/assets/icon/microsoft.svg
entari_plugin_hyw/assets/icon/minimax.png
entari_plugin_hyw/assets/icon/mistral.png
entari_plugin_hyw/assets/icon/nvida.png
entari_plugin_hyw/assets/icon/openai.svg
entari_plugin_hyw/assets/icon/openrouter.png
entari_plugin_hyw/assets/icon/perplexity.svg
entari_plugin_hyw/assets/icon/qwen.png
entari_plugin_hyw/assets/icon/xai.png
entari_plugin_hyw/assets/icon/xiaomi.png
entari_plugin_hyw/assets/icon/zai.png
entari_plugin_hyw/assets/libs/highlight.css
entari_plugin_hyw/assets/libs/highlight.js
entari_plugin_hyw/assets/libs/katex-auto-render.js
entari_plugin_hyw/assets/libs/katex.css
entari_plugin_hyw/assets/libs/katex.js
entari_plugin_hyw/assets/libs/tailwind.css
entari_plugin_hyw/core/__init__.py
entari_plugin_hyw/core/config.py
entari_plugin_hyw/core/history.py
entari_plugin_hyw/core/hyw.py
entari_plugin_hyw/core/pipeline.py
entari_plugin_hyw/core/render.py
entari_plugin_hyw/utils/__init__.py
entari_plugin_hyw/utils/browser.py
entari_plugin_hyw/utils/misc.py
entari_plugin_hyw/utils/playwright_tool.py
entari_plugin_hyw/utils/prompts.py
entari_plugin_hyw/utils/prompts_cn.py
entari_plugin_hyw/utils/search.py
entari_plugin_hyw-3.4.2.dist-info/METADATA
entari_plugin_hyw-3.4.2.dist-info/WHEEL
entari_plugin_hyw-3.4.2.dist-info/top_level.txt
entari_plugin_hyw-3.4.2.dist-info/RECORD
