Metadata-Version: 2.4
Name: entari_plugin_hyw
Version: 3.4.2
Summary: Use large language models to interpret chat messages
Author-email: kumoSleeping <zjr2992@outlook.com>
License: MIT
Project-URL: Homepage, https://github.com/kumoSleeping/entari-plugin-hyw
Project-URL: Repository, https://github.com/kumoSleeping/entari-plugin-hyw
Project-URL: Issue Tracker, https://github.com/kumoSleeping/entari-plugin-hyw/issues
Keywords: entari,llm,ai,bot,chat
Classifier: Development Status :: 3 - Alpha
Classifier: Intended Audience :: Developers
Classifier: License :: OSI Approved :: MIT License
Classifier: Programming Language :: Python :: 3.10
Classifier: Programming Language :: Python :: 3.11
Classifier: Programming Language :: Python :: 3.12
Requires-Python: >=3.10
Requires-Dist: arclet-entari[full]>=0.16.5
Requires-Dist: openai
Requires-Dist: httpx
Requires-Dist: markdown>=3.10
Requires-Dist: crawl4ai>=0.7.8
Requires-Dist: jinja2>=3.0
Requires-Dist: ddgs>=9.10.0
Provides-Extra: dev
Requires-Dist: entari-plugin-server>=0.5.0; extra == "dev"
Requires-Dist: satori-python-adapter-onebot11>=0.2.5; extra == "dev"
